[
  {
    "id": "f5yuQxsMide91X85YdRj1A",
    "alias": "mad-nice-detroit-3",
    "name": "Mad Nice",
    "image_url": "https://s3-media1.fl.yelpcdn.com/bphoto/Cu6MDjfWXY9q0uaGtrqQNA/o.jpg",
    "is_closed": false,
    "url": "https://www.yelp.com/biz/mad-nice-detroit-3?adjust_creative=N0iqFuGe5hug4KyNCfQcCw&utm_campaign=yelp_api_v3&utm_medium=api_v3_business_search&utm_source=N0iqFuGe5hug4KyNCfQcCw",
    "review_count": 42,
    "categories": [
      {
        "alias": "italian",
        "title": "Italian"
      }
    ],
    "rating": 4.0,
    "coordinates": {
      "latitude": 42.34918133,
      "longitude": -83.06506567
    },
    "transactions": [],
    "location": {
      "address1": "4120 Second Ave",
      "address2": null,
      "address3": null,
      "city": "Detroit",
      "zip_code": "48201",
      "country": "US",
      "state": "MI",
      "display_address": [
        "4120 Second Ave",
        "Detroit, MI 48201"
      ]
    },
    "phone": "+13135588000",
    "display_phone": "(313) 558-8000",
    "distance": 2594.430954664236
  },
  {
    "id": "k8ZwQVBv7xpsDGgODG0BhQ",
    "alias": "barda-detroit-detroit",
    "name": "BARDA Detroit",
    "image_url": "https://s3-media2.fl.yelpcdn.com/bphoto/oNlYU9eVBkuK9G2WGrQHvg/o.jpg",
    "is_closed": false,
    "url": "https://www.yelp.com/biz/barda-detroit-detroit?adjust_creative=N0iqFuGe5hug4KyNCfQcCw&utm_campaign=yelp_api_v3&utm_medium=api_v3_business_search&utm_source=N0iqFuGe5hug4KyNCfQcCw",
    "review_count": 125,
    "categories": [
      {
        "alias": "bars",
        "title": "Bars"
      },
      {
        "alias": "argentine",
        "title": "Argentine"
      }
    ],
    "rating": 4.5,
    "coordinates": {
      "latitude": 42.3485,
      "longitude": -83.08786
    },
    "transactions": [],
    "price": "$$$",
    "location": {
      "address1": "4842 Grand River Ave",
      "address2": null,
      "address3": "",
      "city": "Detroit",
      "zip_code": "48208",
      "country": "US",
      "state": "MI",
      "display_address": [
        "4842 Grand River Ave",
        "Detroit, MI 48208"
      ]
    },
    "phone": "+13139525182",
    "display_phone": "(313) 952-5182",
    "distance": 1575.358100146206
  },
  {
    "id": "7ArIKwojlm_Yca29HnGDfQ",
    "alias": "wright-and-company-detroit-3",
    "name": "Wright & Company",
    "image_url": "https://s3-media2.fl.yelpcdn.com/bphoto/qJ6ppc_1LwXNFi391yA1Rw/o.jpg",
    "is_closed": false,
    "url": "https://www.yelp.com/biz/wright-and-company-detroit-3?adjust_creative=N0iqFuGe5hug4KyNCfQcCw&utm_campaign=yelp_api_v3&utm_medium=api_v3_business_search&utm_source=N0iqFuGe5hug4KyNCfQcCw",
    "review_count": 1004,
    "categories": [
      {
        "alias": "gastropubs",
        "title": "Gastropubs"
      },
      {
        "alias": "newamerican",
        "title": "American (New)"
      },
      {
        "alias": "tapasmallplates",
        "title": "Tapas/Small Plates"
      }
    ],
    "rating": 4.5,
    "coordinates": {
      "latitude": 42.33523,
      "longitude": -83.04902
    },
    "transactions": [
      "pickup",
      "delivery"
    ],
    "price": "$$$",
    "location": {
      "address1": "1500 Woodward Ave",
      "address2": "",
      "address3": "",
      "city": "Detroit",
      "zip_code": "48226",
      "country": "US",
      "state": "MI",
      "display_address": [
        "1500 Woodward Ave",
        "Detroit, MI 48226"
      ]
    },
    "phone": "+13139627711",
    "display_phone": "(313) 962-7711",
    "distance": 4587.5803733894845
  },
  {
    "id": "ko1WPwcuifvVoxav9gyZxg",
    "alias": "supergeil-detroit",
    "name": "Supergeil",
    "image_url": "https://s3-media2.fl.yelpcdn.com/bphoto/ZKJFjgGI3DR6mOcdvWtd1w/o.jpg",
    "is_closed": false,
    "url": "https://www.yelp.com/biz/supergeil-detroit?adjust_creative=N0iqFuGe5hug4KyNCfQcCw&utm_campaign=yelp_api_v3&utm_medium=api_v3_business_search&utm_source=N0iqFuGe5hug4KyNCfQcCw",
    "review_count": 111,
    "categories": [
      {
        "alias": "bars",
        "title": "Bars"
      },
      {
        "alias": "mediterranean",
        "title": "Mediterranean"
      },
      {
        "alias": "turkish",
        "title": "Turkish"
      }
    ],
    "rating": 4.5,
    "coordinates": {
      "latitude": 42.331703,
      "longitude": -83.080195
    },
    "transactions": [],
    "price": "$$",
    "location": {
      "address1": "2442 Michigan Ave",
      "address2": null,
      "address3": null,
      "city": "Detroit",
      "zip_code": "48216",
      "country": "US",
      "state": "MI",
      "display_address": [
        "2442 Michigan Ave",
        "Detroit, MI 48216"
      ]
    },
    "phone": "+13134624133",
    "display_phone": "(313) 462-4133",
    "distance": 3553.8009320576784
  },
  {
    "id": "4p1bXdMdETmyU5qhzFxNxw",
    "alias": "selden-standard-detroit",
    "name": "Selden Standard",
    "image_url": "https://s3-media2.fl.yelpcdn.com/bphoto/gyUbwBVcJcE0HuXAVqXqwg/o.jpg",
    "is_closed": false,
    "url": "https://www.yelp.com/biz/selden-standard-detroit?adjust_creative=N0iqFuGe5hug4KyNCfQcCw&utm_campaign=yelp_api_v3&utm_medium=api_v3_business_search&utm_source=N0iqFuGe5hug4KyNCfQcCw",
    "review_count": 1283,
    "categories": [
      {
        "alias": "newamerican",
        "title": "American (New)"
      },
      {
        "alias": "sandwiches",
        "title": "Sandwiches"
      }
    ],
    "rating": 4.5,
    "coordinates": {
      "latitude": 42.34779,
      "longitude": -83.06499
    },
    "transactions": [
      "delivery"
    ],
    "price": "$$",
    "location": {
      "address1": "3921 2nd Ave",
      "address2": "",
      "address3": "",
      "city": "Detroit",
      "zip_code": "48201",
      "country": "US",
      "state": "MI",
      "display_address": [
        "3921 2nd Ave",
        "Detroit, MI 48201"
      ]
    },
    "phone": "+13134385055",
    "display_phone": "(313) 438-5055",
    "distance": 2689.328328755887
  },
  {
    "id": "Xm2A4Xyd-dw4x86qZCV3hw",
    "alias": "chartreuse-detroit",
    "name": "Chartreuse",
    "image_url": "https://s3-media2.fl.yelpcdn.com/bphoto/IN9MzarUkOkRA2D2NejeTw/o.jpg",
    "is_closed": false,
    "url": "https://www.yelp.com/biz/chartreuse-detroit?adjust_creative=N0iqFuGe5hug4KyNCfQcCw&utm_campaign=yelp_api_v3&utm_medium=api_v3_business_search&utm_source=N0iqFuGe5hug4KyNCfQcCw",
    "review_count": 802,
    "categories": [
      {
        "alias": "newamerican",
        "title": "American (New)"
      },
      {
        "alias": "tapasmallplates",
        "title": "Tapas/Small Plates"
      },
      {
        "alias": "cocktailbars",
        "title": "Cocktail Bars"
      }
    ],
    "rating": 4.5,
    "coordinates": {
      "latitude": 42.360517,
      "longitude": -83.066075
    },
    "transactions": [
      "delivery"
    ],
    "price": "$$$",
    "location": {
      "address1": "15 E Kirby St",
      "address2": "Ste D",
      "address3": "",
      "city": "Detroit",
      "zip_code": "48202",
      "country": "US",
      "state": "MI",
      "display_address": [
        "15 E Kirby St",
        "Ste D",
        "Detroit, MI 48202"
      ]
    },
    "phone": "+13138183915",
    "display_phone": "(313) 818-3915",
    "distance": 2055.802317419928
  },
  {
    "id": "M_e9bzbH7yzwcVL_6an9Lw",
    "alias": "oak-and-reel-detroit",
    "name": "Oak & Reel",
    "image_url": "https://s3-media4.fl.yelpcdn.com/bphoto/Ba9LWufgjjDajmLKIgzyTA/o.jpg",
    "is_closed": false,
    "url": "https://www.yelp.com/biz/oak-and-reel-detroit?adjust_creative=N0iqFuGe5hug4KyNCfQcCw&utm_campaign=yelp_api_v3&utm_medium=api_v3_business_search&utm_source=N0iqFuGe5hug4KyNCfQcCw",
    "review_count": 168,
    "categories": [
      {
        "alias": "italian",
        "title": "Italian"
      },
      {
        "alias": "seafood",
        "title": "Seafood"
      }
    ],
    "rating": 4.5,
    "coordinates": {
      "latitude": 42.37222,
      "longitude": -83.0668
    },
    "transactions": [
      "delivery"
    ],
    "location": {
      "address1": "2921 E Grand Blvd",
      "address2": "Ste 100",
      "address3": null,
      "city": "Detroit",
      "zip_code": "48202",
      "country": "US",
      "state": "MI",
      "display_address": [
        "2921 E Grand Blvd",
        "Ste 100",
        "Detroit, MI 48202"
      ]
    },
    "phone": "+13132709600",
    "display_phone": "(313) 270-9600",
    "distance": 2257.4971663556707
  },
  {
    "id": "JU83fjqfc-8OF_60mvgVvA",
    "alias": "babo-detroit-detroit",
    "name": "Babo Detroit",
    "image_url": "https://s3-media4.fl.yelpcdn.com/bphoto/AXBsVzMcfCVxsnQqCkMASg/o.jpg",
    "is_closed": false,
    "url": "https://www.yelp.com/biz/babo-detroit-detroit?adjust_creative=N0iqFuGe5hug4KyNCfQcCw&utm_campaign=yelp_api_v3&utm_medium=api_v3_business_search&utm_source=N0iqFuGe5hug4KyNCfQcCw",
    "review_count": 201,
    "categories": [
      {
        "alias": "newamerican",
        "title": "American (New)"
      },
      {
        "alias": "breakfast_brunch",
        "title": "Breakfast & Brunch"
      }
    ],
    "rating": 4.5,
    "coordinates": {
      "latitude": 42.360556249668,
      "longitude": -83.0664664036942
    },
    "transactions": [
      "pickup",
      "delivery"
    ],
    "price": "$$",
    "location": {
      "address1": "15 E Kirby St",
      "address2": "Ste 115",
      "address3": null,
      "city": "Detroit",
      "zip_code": "48202",
      "country": "US",
      "state": "MI",
      "display_address": [
        "15 E Kirby St",
        "Ste 115",
        "Detroit, MI 48202"
      ]
    },
    "phone": "+13139746159",
    "display_phone": "(313) 974-6159",
    "distance": 2023.2055640365672
  },
  {
    "id": "UdO_uBm3sIM5DwaE8XIpbg",
    "alias": "grey-ghost-detroit-detroit",
    "name": "Grey Ghost Detroit",
    "image_url": "https://s3-media3.fl.yelpcdn.com/bphoto/hxHVMvS--_OCZfcMfW0u1A/o.jpg",
    "is_closed": false,
    "url": "https://www.yelp.com/biz/grey-ghost-detroit-detroit?adjust_creative=N0iqFuGe5hug4KyNCfQcCw&utm_campaign=yelp_api_v3&utm_medium=api_v3_business_search&utm_source=N0iqFuGe5hug4KyNCfQcCw",
    "review_count": 969,
    "categories": [
      {
        "alias": "tradamerican",
        "title": "American (Traditional)"
      },
      {
        "alias": "beerbar",
        "title": "Beer Bar"
      },
      {
        "alias": "cocktailbars",
        "title": "Cocktail Bars"
      }
    ],
    "rating": 4.0,
    "coordinates": {
      "latitude": 42.3451704384376,
      "longitude": -83.0555171146989
    },
    "transactions": [
      "delivery"
    ],
    "price": "$$$",
    "location": {
      "address1": "47 Watson St",
      "address2": "",
      "address3": null,
      "city": "Detroit",
      "zip_code": "48201",
      "country": "US",
      "state": "MI",
      "display_address": [
        "47 Watson St",
        "Detroit, MI 48201"
      ]
    },
    "phone": "+13132626534",
    "display_phone": "(313) 262-6534",
    "distance": 3492.5469868064874
  },
  {
    "id": "9zI10-FuCxKqd0FAHwUFRA",
    "alias": "lumen-detroit-detroit-2",
    "name": "Lumen Detroit",
    "image_url": "https://s3-media2.fl.yelpcdn.com/bphoto/_U9ATgTC_RpVJ9bJ3tKweA/o.jpg",
    "is_closed": false,
    "url": "https://www.yelp.com/biz/lumen-detroit-detroit-2?adjust_creative=N0iqFuGe5hug4KyNCfQcCw&utm_campaign=yelp_api_v3&utm_medium=api_v3_business_search&utm_source=N0iqFuGe5hug4KyNCfQcCw",
    "review_count": 439,
    "categories": [
      {
        "alias": "newamerican",
        "title": "American (New)"
      }
    ],
    "rating": 4.0,
    "coordinates": {
      "latitude": 42.3345218,
      "longitude": -83.0546893
    },
    "transactions": [
      "delivery"
    ],
    "price": "$$",
    "location": {
      "address1": "1903 Grand River Ave",
      "address2": "",
      "address3": null,
      "city": "Detroit",
      "zip_code": "48226",
      "country": "US",
      "state": "MI",
      "display_address": [
        "1903 Grand River Ave",
        "Detroit, MI 48226"
      ]
    },
    "phone": "+13136265005",
    "display_phone": "(313) 626-5005",
    "distance": 4307.851198064722
  },
  {
    "id": "wg7XFjSpK7HHHLtt0Sb88w",
    "alias": "basan-detroit-detroit",
    "name": "Basan Detroit",
    "image_url": "https://s3-media2.fl.yelpcdn.com/bphoto/pZODI1Q7gjmX0N-ISWnr0Q/o.jpg",
    "is_closed": false,
    "url": "https://www.yelp.com/biz/basan-detroit-detroit?adjust_creative=N0iqFuGe5hug4KyNCfQcCw&utm_campaign=yelp_api_v3&utm_medium=api_v3_business_search&utm_source=N0iqFuGe5hug4KyNCfQcCw",
    "review_count": 41,
    "categories": [
      {
        "alias": "cafes",
        "title": "Cafes"
      }
    ],
    "rating": 4.0,
    "coordinates": {
      "latitude": 42.34147,
      "longitude": -83.05672
    },
    "transactions": [],
    "location": {
      "address1": "2703 Park Ave",
      "address2": null,
      "address3": "",
      "city": "Detroit",
      "zip_code": "48201",
      "country": "US",
      "state": "MI",
      "display_address": [
        "2703 Park Ave",
        "Detroit, MI 48201"
      ]
    },
    "phone": "+13134812703",
    "display_phone": "(313) 481-2703",
    "distance": 3657.8287171890215
  },
  {
    "id": "M0XcvvUYkZmbG5ppG1oqvw",
    "alias": "bar-pigalle-detroit",
    "name": "Bar Pigalle",
    "image_url": "https://s3-media2.fl.yelpcdn.com/bphoto/m91dBqMtppz7_WTCSNycow/o.jpg",
    "is_closed": false,
    "url": "https://www.yelp.com/biz/bar-pigalle-detroit?adjust_creative=N0iqFuGe5hug4KyNCfQcCw&utm_campaign=yelp_api_v3&utm_medium=api_v3_business_search&utm_source=N0iqFuGe5hug4KyNCfQcCw",
    "review_count": 58,
    "categories": [
      {
        "alias": "cocktailbars",
        "title": "Cocktail Bars"
      },
      {
        "alias": "french",
        "title": "French"
      },
      {
        "alias": "wine_bars",
        "title": "Wine Bars"
      }
    ],
    "rating": 4.5,
    "coordinates": {
      "latitude": 42.34494549457217,
      "longitude": -83.0539818
    },
    "transactions": [],
    "location": {
      "address1": "2915 John R St",
      "address2": null,
      "address3": "",
      "city": "Detroit",
      "zip_code": "48201",
      "country": "US",
      "state": "MI",
      "display_address": [
        "2915 John R St",
        "Detroit, MI 48201"
      ]
    },
    "phone": "+13134979200",
    "display_phone": "(313) 497-9200",
    "distance": 3611.8652057113763
  },
  {
    "id": "gL6l1EqphkyLqER5lgmReg",
    "alias": "standby-detroit",
    "name": "Standby",
    "image_url": "https://s3-media2.fl.yelpcdn.com/bphoto/q7ZhntueowcD7Jeop-RqlQ/o.jpg",
    "is_closed": false,
    "url": "https://www.yelp.com/biz/standby-detroit?adjust_creative=N0iqFuGe5hug4KyNCfQcCw&utm_campaign=yelp_api_v3&utm_medium=api_v3_business_search&utm_source=N0iqFuGe5hug4KyNCfQcCw",
    "review_count": 625,
    "categories": [
      {
        "alias": "newamerican",
        "title": "American (New)"
      },
      {
        "alias": "cocktailbars",
        "title": "Cocktail Bars"
      }
    ],
    "rating": 4.5,
    "coordinates": {
      "latitude": 42.3344844608147,
      "longitude": -83.0461140631014
    },
    "transactions": [
      "delivery"
    ],
    "price": "$$",
    "location": {
      "address1": "225 Gratiot Ave",
      "address2": "",
      "address3": "",
      "city": "Detroit",
      "zip_code": "48226",
      "country": "US",
      "state": "MI",
      "display_address": [
        "225 Gratiot Ave",
        "Detroit, MI 48226"
      ]
    },
    "phone": "+13132415719",
    "display_phone": "(313) 241-5719",
    "distance": 4826.2654838865365
  },
  {
    "id": "DsXh8jluV0BaSkVhxQre8Q",
    "alias": "shewolf-pastificio-and-bar-detroit",
    "name": "SheWolf Pastificio & Bar",
    "image_url": "https://s3-media3.fl.yelpcdn.com/bphoto/V6pd4eRR3JRvd_iX92WPTQ/o.jpg",
    "is_closed": false,
    "url": "https://www.yelp.com/biz/shewolf-pastificio-and-bar-detroit?adjust_creative=N0iqFuGe5hug4KyNCfQcCw&utm_campaign=yelp_api_v3&utm_medium=api_v3_business_search&utm_source=N0iqFuGe5hug4KyNCfQcCw",
    "review_count": 439,
    "categories": [
      {
        "alias": "italian",
        "title": "Italian"
      },
      {
        "alias": "bars",
        "title": "Bars"
      }
    ],
    "rating": 4.0,
    "coordinates": {
      "latitude": 42.347953002822436,
      "longitude": -83.06269721729974
    },
    "transactions": [
      "delivery"
    ],
    "price": "$$$",
    "location": {
      "address1": "438 Selden St",
      "address2": "",
      "address3": null,
      "city": "Detroit",
      "zip_code": "48201",
      "country": "US",
      "state": "MI",
      "display_address": [
        "438 Selden St",
        "Detroit, MI 48201"
      ]
    },
    "phone": "+13133153992",
    "display_phone": "(313) 315-3992",
    "distance": 2830.584333531209
  },
  {
    "id": "3Nbs9f7DxP3siSu1pjLj1w",
    "alias": "takoi-detroit",
    "name": "Takoi",
    "image_url": "https://s3-media2.fl.yelpcdn.com/bphoto/HxCYQwQDGQKa1JQv5qjXow/o.jpg",
    "is_closed": false,
    "url": "https://www.yelp.com/biz/takoi-detroit?adjust_creative=N0iqFuGe5hug4KyNCfQcCw&utm_campaign=yelp_api_v3&utm_medium=api_v3_business_search&utm_source=N0iqFuGe5hug4KyNCfQcCw",
    "review_count": 656,
    "categories": [
      {
        "alias": "thai",
        "title": "Thai"
      },
      {
        "alias": "panasian",
        "title": "Pan Asian"
      },
      {
        "alias": "cocktailbars",
        "title": "Cocktail Bars"
      }
    ],
    "rating": 4.5,
    "coordinates": {
      "latitude": 42.3316432369511,
      "longitude": -83.0808343566223
    },
    "transactions": [
      "pickup",
      "delivery"
    ],
    "price": "$$",
    "location": {
      "address1": "2520 Michigan Ave",
      "address2": "",
      "address3": "",
      "city": "Detroit",
      "zip_code": "48216",
      "country": "US",
      "state": "MI",
      "display_address": [
        "2520 Michigan Ave",
        "Detroit, MI 48216"
      ]
    },
    "phone": "+13138552864",
    "display_phone": "(313) 855-2864",
    "distance": 3532.5127445209378
  },
  {
    "id": "HYrqw4xlLCNDptBHGrTIbQ",
    "alias": "dime-store-detroit-4",
    "name": "Dime Store",
    "image_url": "https://s3-media2.fl.yelpcdn.com/bphoto/gu66zixLlfvcdbTfoS-OcA/o.jpg",
    "is_closed": false,
    "url": "https://www.yelp.com/biz/dime-store-detroit-4?adjust_creative=N0iqFuGe5hug4KyNCfQcCw&utm_campaign=yelp_api_v3&utm_medium=api_v3_business_search&utm_source=N0iqFuGe5hug4KyNCfQcCw",
    "review_count": 1796,
    "categories": [
      {
        "alias": "breakfast_brunch",
        "title": "Breakfast & Brunch"
      },
      {
        "alias": "newamerican",
        "title": "American (New)"
      },
      {
        "alias": "diners",
        "title": "Diners"
      }
    ],
    "rating": 4.5,
    "coordinates": {
      "latitude": 42.3308060633157,
      "longitude": -83.0479924085636
    },
    "transactions": [
      "delivery"
    ],
    "price": "$$",
    "location": {
      "address1": "719 Griswold St",
      "address2": "Ste 180",
      "address3": "",
      "city": "Detroit",
      "zip_code": "48226",
      "country": "US",
      "state": "MI",
      "display_address": [
        "719 Griswold St",
        "Ste 180",
        "Detroit, MI 48226"
      ]
    },
    "phone": "+13139629106",
    "display_phone": "(313) 962-9106",
    "distance": 4989.731483351786
  },
  {
    "id": "aVOoohl4rV4yrOebhiZiWQ",
    "alias": "smith-and-co-detroit",
    "name": "Smith & Co",
    "image_url": "https://s3-media1.fl.yelpcdn.com/bphoto/RmC9vRhfyHbdlzphXHv2xg/o.jpg",
    "is_closed": false,
    "url": "https://www.yelp.com/biz/smith-and-co-detroit?adjust_creative=N0iqFuGe5hug4KyNCfQcCw&utm_campaign=yelp_api_v3&utm_medium=api_v3_business_search&utm_source=N0iqFuGe5hug4KyNCfQcCw",
    "review_count": 125,
    "categories": [
      {
        "alias": "newamerican",
        "title": "American (New)"
      }
    ],
    "rating": 4.0,
    "coordinates": {
      "latitude": 42.34744772504895,
      "longitude": -83.06562333681428
    },
    "transactions": [
      "delivery"
    ],
    "price": "$$",
    "location": {
      "address1": "644 Selden St",
      "address2": null,
      "address3": "",
      "city": "Detroit",
      "zip_code": "48201",
      "country": "US",
      "state": "MI",
      "display_address": [
        "644 Selden St",
        "Detroit, MI 48201"
      ]
    },
    "phone": "+13136381695",
    "display_phone": "(313) 638-1695",
    "distance": 2671.8810050220322
  },
  {
    "id": "ngu3My-XGzNNL7Bxul5ulQ",
    "alias": "ottava-via-detroit",
    "name": "Ottava Via",
    "image_url": "https://s3-media3.fl.yelpcdn.com/bphoto/ZiBFwqNnXOOOrSOg5Txv1g/o.jpg",
    "is_closed": false,
    "url": "https://www.yelp.com/biz/ottava-via-detroit?adjust_creative=N0iqFuGe5hug4KyNCfQcCw&utm_campaign=yelp_api_v3&utm_medium=api_v3_business_search&utm_source=N0iqFuGe5hug4KyNCfQcCw",
    "review_count": 827,
    "categories": [
      {
        "alias": "pizza",
        "title": "Pizza"
      },
      {
        "alias": "italian",
        "title": "Italian"
      },
      {
        "alias": "sandwiches",
        "title": "Sandwiches"
      }
    ],
    "rating": 4.0,
    "coordinates": {
      "latitude": 42.331716,
      "longitude": -83.065696
    },
    "transactions": [
      "delivery"
    ],
    "price": "$$",
    "location": {
      "address1": "1400 Michigan Ave",
      "address2": "",
      "address3": "",
      "city": "Detroit",
      "zip_code": "48216",
      "country": "US",
      "state": "MI",
      "display_address": [
        "1400 Michigan Ave",
        "Detroit, MI 48216"
      ]
    },
    "phone": "+13139625500",
    "display_phone": "(313) 962-5500",
    "distance": 4004.8432037838556
  },
  {
    "id": "65pRcC4awElAnzH4io9Chw",
    "alias": "batch-brewing-company-detroit",
    "name": "Batch Brewing Company",
    "image_url": "https://s3-media1.fl.yelpcdn.com/bphoto/-L3fYUp8ozuMXhDEycNZbQ/o.jpg",
    "is_closed": false,
    "url": "https://www.yelp.com/biz/batch-brewing-company-detroit?adjust_creative=N0iqFuGe5hug4KyNCfQcCw&utm_campaign=yelp_api_v3&utm_medium=api_v3_business_search&utm_source=N0iqFuGe5hug4KyNCfQcCw",
    "review_count": 458,
    "categories": [
      {
        "alias": "newamerican",
        "title": "American (New)"
      },
      {
        "alias": "brewpubs",
        "title": "Brewpubs"
      }
    ],
    "rating": 4.5,
    "coordinates": {
      "latitude": 42.3283429981483,
      "longitude": -83.0632939479199
    },
    "transactions": [
      "delivery"
    ],
    "price": "$$",
    "location": {
      "address1": "1400 Porter St",
      "address2": "",
      "address3": "",
      "city": "Detroit",
      "zip_code": "48216",
      "country": "US",
      "state": "MI",
      "display_address": [
        "1400 Porter St",
        "Detroit, MI 48216"
      ]
    },
    "phone": "+13133388008",
    "display_phone": "(313) 338-8008",
    "distance": 4428.017869705115
  },
  {
    "id": "ioFyTODz0m_z8dTIidyq5A",
    "alias": "bash-original-izakaya-detroit",
    "name": "Bash Original Izakaya",
    "image_url": "https://s3-media3.fl.yelpcdn.com/bphoto/rZ18cwKcMJL19U3mHnengA/o.jpg",
    "is_closed": false,
    "url": "https://www.yelp.com/biz/bash-original-izakaya-detroit?adjust_creative=N0iqFuGe5hug4KyNCfQcCw&utm_campaign=yelp_api_v3&utm_medium=api_v3_business_search&utm_source=N0iqFuGe5hug4KyNCfQcCw",
    "review_count": 113,
    "categories": [
      {
        "alias": "sushi",
        "title": "Sushi Bars"
      },
      {
        "alias": "izakaya",
        "title": "Izakaya"
      }
    ],
    "rating": 4.5,
    "coordinates": {
      "latitude": 42.352967,
      "longitude": -83.079469
    },
    "transactions": [
      "pickup",
      "delivery"
    ],
    "location": {
      "address1": "5069 Trumbull St",
      "address2": "",
      "address3": null,
      "city": "Detroit",
      "zip_code": "48208",
      "country": "US",
      "state": "MI",
      "display_address": [
        "5069 Trumbull St",
        "Detroit, MI 48208"
      ]
    },
    "phone": "+13137887208",
    "display_phone": "(313) 788-7208",
    "distance": 1420.5214094778858
  },
  {
    "id": "-mguM6V0E2XTx3A1qBLSyw",
    "alias": "baobab-fare-detroit",
    "name": "Baobab Fare",
    "image_url": "https://s3-media1.fl.yelpcdn.com/bphoto/PiIC6_kcswZTgbWFHqCy-Q/o.jpg",
    "is_closed": false,
    "url": "https://www.yelp.com/biz/baobab-fare-detroit?adjust_creative=N0iqFuGe5hug4KyNCfQcCw&utm_campaign=yelp_api_v3&utm_medium=api_v3_business_search&utm_source=N0iqFuGe5hug4KyNCfQcCw",
    "review_count": 205,
    "categories": [
      {
        "alias": "coffee",
        "title": "Coffee & Tea"
      },
      {
        "alias": "african",
        "title": "African"
      },
      {
        "alias": "juicebars",
        "title": "Juice Bars & Smoothies"
      }
    ],
    "rating": 5.0,
    "coordinates": {
      "latitude": 42.3700146,
      "longitude": -83.0729392
    },
    "transactions": [
      "pickup",
      "delivery"
    ],
    "price": "$$",
    "location": {
      "address1": "6568 Woodward Ave",
      "address2": null,
      "address3": null,
      "city": "Detroit",
      "zip_code": "48202",
      "country": "US",
      "state": "MI",
      "display_address": [
        "6568 Woodward Ave",
        "Detroit, MI 48202"
      ]
    },
    "phone": "+13132653093",
    "display_phone": "(313) 265-3093",
    "distance": 1706.1411042264303
  },
  {
    "id": "MlKmMAF_rFjgy0nX_fk8Mw",
    "alias": "cork-and-gabel-detroit",
    "name": "Cork & Gabel",
    "image_url": "https://s3-media1.fl.yelpcdn.com/bphoto/egDxSVGb5Ev8SemKEMEXbA/o.jpg",
    "is_closed": false,
    "url": "https://www.yelp.com/biz/cork-and-gabel-detroit?adjust_creative=N0iqFuGe5hug4KyNCfQcCw&utm_campaign=yelp_api_v3&utm_medium=api_v3_business_search&utm_source=N0iqFuGe5hug4KyNCfQcCw",
    "review_count": 164,
    "categories": [
      {
        "alias": "comfortfood",
        "title": "Comfort Food"
      },
      {
        "alias": "italian",
        "title": "Italian"
      },
      {
        "alias": "irish",
        "title": "Irish"
      }
    ],
    "rating": 4.0,
    "coordinates": {
      "latitude": 42.33111,
      "longitude": -83.07941
    },
    "transactions": [],
    "price": "$$",
    "location": {
      "address1": "2415 Michigan Ave",
      "address2": "",
      "address3": null,
      "city": "Detroit",
      "zip_code": "48216",
      "country": "US",
      "state": "MI",
      "display_address": [
        "2415 Michigan Ave",
        "Detroit, MI 48216"
      ]
    },
    "phone": "+13136382261",
    "display_phone": "(313) 638-2261",
    "distance": 3618.8790772493226
  },
  {
    "id": "fmcHbCeBsXEEdY4btGBcPg",
    "alias": "yum-village-detroit",
    "name": "Yum Village",
    "image_url": "https://s3-media4.fl.yelpcdn.com/bphoto/9FXA3fH6rhospSFajtWUFw/o.jpg",
    "is_closed": false,
    "url": "https://www.yelp.com/biz/yum-village-detroit?adjust_creative=N0iqFuGe5hug4KyNCfQcCw&utm_campaign=yelp_api_v3&utm_medium=api_v3_business_search&utm_source=N0iqFuGe5hug4KyNCfQcCw",
    "review_count": 196,
    "categories": [
      {
        "alias": "caribbean",
        "title": "Caribbean"
      },
      {
        "alias": "african",
        "title": "African"
      },
      {
        "alias": "personalchefs",
        "title": "Personal Chefs"
      }
    ],
    "rating": 4.0,
    "coordinates": {
      "latitude": 42.369378,
      "longitude": -83.072277
    },
    "transactions": [
      "pickup",
      "delivery"
    ],
    "price": "$$",
    "location": {
      "address1": "6500 Woodward Ave",
      "address2": "",
      "address3": null,
      "city": "Detroit",
      "zip_code": "48202",
      "country": "US",
      "state": "MI",
      "display_address": [
        "6500 Woodward Ave",
        "Detroit, MI 48202"
      ]
    },
    "phone": "+13133346099",
    "display_phone": "(313) 334-6099",
    "distance": 1712.9545631410335
  },
  {
    "id": "QUPAXavtWd6LKnvsWV6ywQ",
    "alias": "detroit-shipping-company-detroit-2",
    "name": "Detroit Shipping Company",
    "image_url": "https://s3-media2.fl.yelpcdn.com/bphoto/Uezm1F47JFrV-AaN8F6Q8g/o.jpg",
    "is_closed": false,
    "url": "https://www.yelp.com/biz/detroit-shipping-company-detroit-2?adjust_creative=N0iqFuGe5hug4KyNCfQcCw&utm_campaign=yelp_api_v3&utm_medium=api_v3_business_search&utm_source=N0iqFuGe5hug4KyNCfQcCw",
    "review_count": 373,
    "categories": [
      {
        "alias": "beergardens",
        "title": "Beer Gardens"
      },
      {
        "alias": "food_court",
        "title": "Food Court"
      }
    ],
    "rating": 4.0,
    "coordinates": {
      "latitude": 42.34401907742649,
      "longitude": -83.06146026886441
    },
    "transactions": [
      "delivery"
    ],
    "price": "$$",
    "location": {
      "address1": "474 Peterboro St",
      "address2": "",
      "address3": null,
      "city": "Detroit",
      "zip_code": "48201",
      "country": "US",
      "state": "MI",
      "display_address": [
        "474 Peterboro St",
        "Detroit, MI 48201"
      ]
    },
    "phone": "+13134624973",
    "display_phone": "(313) 462-4973",
    "distance": 3178.559257086225
  },
  {
    "id": "yRhM23WYVMS1lYenbVjr8A",
    "alias": "ima-izakaya-detroit",
    "name": "Ima Izakaya",
    "image_url": "https://s3-media2.fl.yelpcdn.com/bphoto/EbNfhLy4CaM3m91qcj25GA/o.jpg",
    "is_closed": false,
    "url": "https://www.yelp.com/biz/ima-izakaya-detroit?adjust_creative=N0iqFuGe5hug4KyNCfQcCw&utm_campaign=yelp_api_v3&utm_medium=api_v3_business_search&utm_source=N0iqFuGe5hug4KyNCfQcCw",
    "review_count": 51,
    "categories": [
      {
        "alias": "izakaya",
        "title": "Izakaya"
      }
    ],
    "rating": 4.5,
    "coordinates": {
      "latitude": 42.33163354764796,
      "longitude": -83.0753548
    },
    "transactions": [
      "pickup",
      "delivery"
    ],
    "price": "$$",
    "location": {
      "address1": "2100 Michigan Ave",
      "address2": null,
      "address3": "",
      "city": "Detroit",
      "zip_code": "48216",
      "country": "US",
      "state": "MI",
      "display_address": [
        "2100 Michigan Ave",
        "Detroit, MI 48216"
      ]
    },
    "phone": "+13133069485",
    "display_phone": "(313) 306-9485",
    "distance": 3665.6953054075957
  },
  {
    "id": "zZldbS9xvdEQuMBzOVwzvA",
    "alias": "olin-bar-and-kitchen-detroit",
    "name": "Olin Bar & Kitchen",
    "image_url": "https://s3-media1.fl.yelpcdn.com/bphoto/EY6Ap9sZq2_CdBXcD_6EYw/o.jpg",
    "is_closed": false,
    "url": "https://www.yelp.com/biz/olin-bar-and-kitchen-detroit?adjust_creative=N0iqFuGe5hug4KyNCfQcCw&utm_campaign=yelp_api_v3&utm_medium=api_v3_business_search&utm_source=N0iqFuGe5hug4KyNCfQcCw",
    "review_count": 164,
    "categories": [
      {
        "alias": "newamerican",
        "title": "American (New)"
      },
      {
        "alias": "tapasmallplates",
        "title": "Tapas/Small Plates"
      }
    ],
    "rating": 4.5,
    "coordinates": {
      "latitude": 42.334564,
      "longitude": -83.048094
    },
    "transactions": [],
    "price": "$$$",
    "location": {
      "address1": "25 E Grand River Ave",
      "address2": "",
      "address3": null,
      "city": "Detroit",
      "zip_code": "48226",
      "country": "US",
      "state": "MI",
      "display_address": [
        "25 E Grand River Ave",
        "Detroit, MI 48226"
      ]
    },
    "phone": "+13137741190",
    "display_phone": "(313) 774-1190",
    "distance": 4697.367918586336
  },
  {
    "id": "VOjmQVpCLjRlOkGtLDLFYQ",
    "alias": "the-elephant-room-detroit",
    "name": "The Elephant Room",
    "image_url": "https://s3-media1.fl.yelpcdn.com/bphoto/zMatxAMwShlG7vpxIXstZA/o.jpg",
    "is_closed": false,
    "url": "https://www.yelp.com/biz/the-elephant-room-detroit?adjust_creative=N0iqFuGe5hug4KyNCfQcCw&utm_campaign=yelp_api_v3&utm_medium=api_v3_business_search&utm_source=N0iqFuGe5hug4KyNCfQcCw",
    "review_count": 86,
    "categories": [
      {
        "alias": "tradamerican",
        "title": "American (Traditional)"
      },
      {
        "alias": "cocktailbars",
        "title": "Cocktail Bars"
      }
    ],
    "rating": 4.0,
    "coordinates": {
      "latitude": 42.33242,
      "longitude": -83.04129
    },
    "transactions": [
      "pickup",
      "delivery"
    ],
    "location": {
      "address1": "439 E Congress St",
      "address2": "",
      "address3": null,
      "city": "Detroit",
      "zip_code": "48226",
      "country": "US",
      "state": "MI",
      "display_address": [
        "439 E Congress St",
        "Detroit, MI 48226"
      ]
    },
    "phone": "+13134624889",
    "display_phone": "(313) 462-4889",
    "distance": 5274.307079976423
  },
  {
    "id": "zpMaHHdBtXphaKkRy5r5NA",
    "alias": "union-assembly-detroit",
    "name": "Union Assembly",
    "image_url": "https://s3-media1.fl.yelpcdn.com/bphoto/kHXkh_GXxjqKIKlTXKfHUQ/o.jpg",
    "is_closed": false,
    "url": "https://www.yelp.com/biz/union-assembly-detroit?adjust_creative=N0iqFuGe5hug4KyNCfQcCw&utm_campaign=yelp_api_v3&utm_medium=api_v3_business_search&utm_source=N0iqFuGe5hug4KyNCfQcCw",
    "review_count": 112,
    "categories": [
      {
        "alias": "newamerican",
        "title": "American (New)"
      },
      {
        "alias": "pizza",
        "title": "Pizza"
      }
    ],
    "rating": 4.0,
    "coordinates": {
      "latitude": 42.338024,
      "longitude": -83.051814
    },
    "transactions": [],
    "price": "$$",
    "location": {
      "address1": "2131 Woodward Ave",
      "address2": null,
      "address3": "",
      "city": "Detroit",
      "zip_code": "48201",
      "country": "US",
      "state": "MI",
      "display_address": [
        "2131 Woodward Ave",
        "Detroit, MI 48201"
      ]
    },
    "phone": "+13138005173",
    "display_phone": "(313) 800-5173",
    "distance": 4214.383085656719
  },
  {
    "id": "unpNAU7aIF11_VQvZXUOWg",
    "alias": "the-apparatus-room-detroit",
    "name": "The Apparatus Room",
    "image_url": "https://s3-media4.fl.yelpcdn.com/bphoto/cMFjpaXrWArCsX5QFt27tQ/o.jpg",
    "is_closed": false,
    "url": "https://www.yelp.com/biz/the-apparatus-room-detroit?adjust_creative=N0iqFuGe5hug4KyNCfQcCw&utm_campaign=yelp_api_v3&utm_medium=api_v3_business_search&utm_source=N0iqFuGe5hug4KyNCfQcCw",
    "review_count": 694,
    "categories": [
      {
        "alias": "newamerican",
        "title": "American (New)"
      },
      {
        "alias": "cocktailbars",
        "title": "Cocktail Bars"
      }
    ],
    "rating": 4.0,
    "coordinates": {
      "latitude": 42.3281585909956,
      "longitude": -83.04851272487
    },
    "transactions": [
      "pickup",
      "delivery"
    ],
    "price": "$$$",
    "location": {
      "address1": "250 W Larned St",
      "address2": "",
      "address3": null,
      "city": "Detroit",
      "zip_code": "48226",
      "country": "US",
      "state": "MI",
      "display_address": [
        "250 W Larned St",
        "Detroit, MI 48226"
      ]
    },
    "phone": "+13138005600",
    "display_phone": "(313) 800-5600",
    "distance": 5173.083678291132
  },
  {
    "id": "EMTbwv0DI2QERgioIoblmw",
    "alias": "the-yard-at-corktown-detroit-3",
    "name": "The Yard at Corktown",
    "image_url": "https://s3-media4.fl.yelpcdn.com/bphoto/NkfxxdXLCSFYwj_ZGK7qtg/o.jpg",
    "is_closed": false,
    "url": "https://www.yelp.com/biz/the-yard-at-corktown-detroit-3?adjust_creative=N0iqFuGe5hug4KyNCfQcCw&utm_campaign=yelp_api_v3&utm_medium=api_v3_business_search&utm_source=N0iqFuGe5hug4KyNCfQcCw",
    "review_count": 2,
    "categories": [
      {
        "alias": "bars",
        "title": "Bars"
      },
      {
        "alias": "tacos",
        "title": "Tacos"
      },
      {
        "alias": "tabletopgames",
        "title": "Tabletop Games"
      }
    ],
    "rating": 5.0,
    "coordinates": {
      "latitude": 42.3311306,
      "longitude": -83.06495509999999
    },
    "transactions": [],
    "location": {
      "address1": "1375 Michigan Ave",
      "address2": null,
      "address3": "",
      "city": "Detroit",
      "zip_code": "48226",
      "country": "US",
      "state": "MI",
      "display_address": [
        "1375 Michigan Ave",
        "Detroit, MI 48226"
      ]
    },
    "phone": "+13132858080",
    "display_phone": "(313) 285-8080",
    "distance": 4092.1128254108594
  },
  {
    "id": "TkLcUfsNpPMCf-ksOv7Yeg",
    "alias": "ima-detroit-2",
    "name": "ima",
    "image_url": "https://s3-media2.fl.yelpcdn.com/bphoto/tBH1vGcloqCA95AzFMxpwg/o.jpg",
    "is_closed": false,
    "url": "https://www.yelp.com/biz/ima-detroit-2?adjust_creative=N0iqFuGe5hug4KyNCfQcCw&utm_campaign=yelp_api_v3&utm_medium=api_v3_business_search&utm_source=N0iqFuGe5hug4KyNCfQcCw",
    "review_count": 138,
    "categories": [
      {
        "alias": "ramen",
        "title": "Ramen"
      },
      {
        "alias": "noodles",
        "title": "Noodles"
      },
      {
        "alias": "soup",
        "title": "Soup"
      }
    ],
    "rating": 4.0,
    "coordinates": {
      "latitude": 42.3558225730242,
      "longitude": -83.0663166940212
    },
    "transactions": [
      "pickup",
      "delivery"
    ],
    "price": "$$",
    "location": {
      "address1": "4870 Cass Ave",
      "address2": "",
      "address3": null,
      "city": "Detroit",
      "zip_code": "48201",
      "country": "US",
      "state": "MI",
      "display_address": [
        "4870 Cass Ave",
        "Detroit, MI 48201"
      ]
    },
    "phone": "+13138839788",
    "display_phone": "(313) 883-9788",
    "distance": 2156.445398665847
  },
  {
    "id": "LXY2-zJxovRaiWixlLmRWg",
    "alias": "frita-batidos-detroit",
    "name": "Frita Batidos",
    "image_url": "https://s3-media2.fl.yelpcdn.com/bphoto/Pnrmeofw6CFtP2mr7BFH8A/o.jpg",
    "is_closed": false,
    "url": "https://www.yelp.com/biz/frita-batidos-detroit?adjust_creative=N0iqFuGe5hug4KyNCfQcCw&utm_campaign=yelp_api_v3&utm_medium=api_v3_business_search&utm_source=N0iqFuGe5hug4KyNCfQcCw",
    "review_count": 125,
    "categories": [
      {
        "alias": "burgers",
        "title": "Burgers"
      },
      {
        "alias": "cuban",
        "title": "Cuban"
      }
    ],
    "rating": 4.5,
    "coordinates": {
      "latitude": 42.3379,
      "longitude": -83.05314
    },
    "transactions": [
      "delivery"
    ],
    "price": "$$",
    "location": {
      "address1": "66 W Columbia St",
      "address2": "",
      "address3": null,
      "city": "Detroit",
      "zip_code": "48201",
      "country": "US",
      "state": "MI",
      "display_address": [
        "66 W Columbia St",
        "Detroit, MI 48201"
      ]
    },
    "phone": "+13137254100",
    "display_phone": "(313) 725-4100",
    "distance": 4146.333656621955
  },
  {
    "id": "T6Zl8NssV2qy8Vn9c9ueDQ",
    "alias": "bobcat-bonnies-detroit",
    "name": "Bobcat Bonnie's",
    "image_url": "https://s3-media4.fl.yelpcdn.com/bphoto/gArh1teeMwOIUiewpA7RAA/o.jpg",
    "is_closed": false,
    "url": "https://www.yelp.com/biz/bobcat-bonnies-detroit?adjust_creative=N0iqFuGe5hug4KyNCfQcCw&utm_campaign=yelp_api_v3&utm_medium=api_v3_business_search&utm_source=N0iqFuGe5hug4KyNCfQcCw",
    "review_count": 637,
    "categories": [
      {
        "alias": "gastropubs",
        "title": "Gastropubs"
      },
      {
        "alias": "breakfast_brunch",
        "title": "Breakfast & Brunch"
      },
      {
        "alias": "cocktailbars",
        "title": "Cocktail Bars"
      }
    ],
    "rating": 4.0,
    "coordinates": {
      "latitude": 42.3315449,
      "longitude": -83.0707433
    },
    "transactions": [
      "pickup",
      "delivery"
    ],
    "price": "$$",
    "location": {
      "address1": "1800 Michigan Ave",
      "address2": "",
      "address3": "",
      "city": "Detroit",
      "zip_code": "48216",
      "country": "US",
      "state": "MI",
      "display_address": [
        "1800 Michigan Ave",
        "Detroit, MI 48216"
      ]
    },
    "phone": "+13139621383",
    "display_phone": "(313) 962-1383",
    "distance": 3811.2199231832187
  },
  {
    "id": "2Gbql_loKmYhuOE40QyVsA",
    "alias": "the-block-detroit",
    "name": "The Block",
    "image_url": "https://s3-media1.fl.yelpcdn.com/bphoto/-sZp6Tv2dlelNFRBh1NN6w/o.jpg",
    "is_closed": false,
    "url": "https://www.yelp.com/biz/the-block-detroit?adjust_creative=N0iqFuGe5hug4KyNCfQcCw&utm_campaign=yelp_api_v3&utm_medium=api_v3_business_search&utm_source=N0iqFuGe5hug4KyNCfQcCw",
    "review_count": 301,
    "categories": [
      {
        "alias": "tradamerican",
        "title": "American (Traditional)"
      }
    ],
    "rating": 4.0,
    "coordinates": {
      "latitude": 42.3497097,
      "longitude": -83.0596056
    },
    "transactions": [
      "delivery"
    ],
    "price": "$$",
    "location": {
      "address1": "3919 Woodward Ave",
      "address2": "",
      "address3": "",
      "city": "Detroit",
      "zip_code": "48201",
      "country": "US",
      "state": "MI",
      "display_address": [
        "3919 Woodward Ave",
        "Detroit, MI 48201"
      ]
    },
    "phone": "+13138320892",
    "display_phone": "(313) 832-0892",
    "distance": 2912.831444934779
  },
  {
    "id": "vm2ac7XVpdriznjvxf4Mow",
    "alias": "second-best-detroit-detroit-2",
    "name": "Second Best Detroit",
    "image_url": "https://s3-media1.fl.yelpcdn.com/bphoto/iO53Q5yXyXGT69iNTXSkYg/o.jpg",
    "is_closed": false,
    "url": "https://www.yelp.com/biz/second-best-detroit-detroit-2?adjust_creative=N0iqFuGe5hug4KyNCfQcCw&utm_campaign=yelp_api_v3&utm_medium=api_v3_business_search&utm_source=N0iqFuGe5hug4KyNCfQcCw",
    "review_count": 96,
    "categories": [
      {
        "alias": "bars",
        "title": "Bars"
      },
      {
        "alias": "tradamerican",
        "title": "American (Traditional)"
      }
    ],
    "rating": 4.0,
    "coordinates": {
      "latitude": 42.344965,
      "longitude": -83.055255
    },
    "transactions": [
      "pickup",
      "delivery"
    ],
    "location": {
      "address1": "42 Watson St",
      "address2": "",
      "address3": "",
      "city": "Detroit",
      "zip_code": "48201",
      "country": "US",
      "state": "MI",
      "display_address": [
        "42 Watson St",
        "Detroit, MI 48201"
      ]
    },
    "phone": "+13133153077",
    "display_phone": "(313) 315-3077",
    "distance": 3523.1310923439614
  },
  {
    "id": "CnCpxcw9r6lgKDk4br8TKA",
    "alias": "bakersfield-detroit",
    "name": "Bakersfield",
    "image_url": "https://s3-media3.fl.yelpcdn.com/bphoto/z6EA8HT4e8RdmafYibm2eg/o.jpg",
    "is_closed": false,
    "url": "https://www.yelp.com/biz/bakersfield-detroit?adjust_creative=N0iqFuGe5hug4KyNCfQcCw&utm_campaign=yelp_api_v3&utm_medium=api_v3_business_search&utm_source=N0iqFuGe5hug4KyNCfQcCw",
    "review_count": 667,
    "categories": [
      {
        "alias": "tacos",
        "title": "Tacos"
      },
      {
        "alias": "bars",
        "title": "Bars"
      }
    ],
    "rating": 4.0,
    "coordinates": {
      "latitude": 42.34518,
      "longitude": -83.05572
    },
    "transactions": [],
    "price": "$$",
    "location": {
      "address1": "3100 Woodward Ave",
      "address2": "",
      "address3": null,
      "city": "Detroit",
      "zip_code": "48201",
      "country": "US",
      "state": "MI",
      "display_address": [
        "3100 Woodward Ave",
        "Detroit, MI 48201"
      ]
    },
    "phone": "+13139747040",
    "display_phone": "(313) 974-7040",
    "distance": 3444.1788991702883
  },
  {
    "id": "fGj2fwdxSuIB3hYPaUq1WQ",
    "alias": "michigan-and-trumbull-detroit-6",
    "name": "Michigan & Trumbull",
    "image_url": "https://s3-media3.fl.yelpcdn.com/bphoto/cnKAkGkx0PQNLe1a2zN0gg/o.jpg",
    "is_closed": false,
    "url": "https://www.yelp.com/biz/michigan-and-trumbull-detroit-6?adjust_creative=N0iqFuGe5hug4KyNCfQcCw&utm_campaign=yelp_api_v3&utm_medium=api_v3_business_search&utm_source=N0iqFuGe5hug4KyNCfQcCw",
    "review_count": 167,
    "categories": [
      {
        "alias": "pizza",
        "title": "Pizza"
      }
    ],
    "rating": 4.5,
    "coordinates": {
      "latitude": 42.3320754543569,
      "longitude": -83.0664473117439
    },
    "transactions": [
      "pickup",
      "delivery"
    ],
    "price": "$$",
    "location": {
      "address1": "1441 W Elizabeth St",
      "address2": null,
      "address3": null,
      "city": "Detroit",
      "zip_code": "48216",
      "country": "US",
      "state": "MI",
      "display_address": [
        "1441 W Elizabeth St",
        "Detroit, MI 48216"
      ]
    },
    "phone": "+13136374992",
    "display_phone": "(313) 637-4992",
    "distance": 3949.0406775488736
  },
  {
    "id": "kvG8Rsie9vE7lQqOvUxRrw",
    "alias": "honest-johns-bar-and-grill-detroit",
    "name": "Honest John's Bar & Grill",
    "image_url": "https://s3-media2.fl.yelpcdn.com/bphoto/nyKhx4zJ2yU4TGIQ1SmdMg/o.jpg",
    "is_closed": false,
    "url": "https://www.yelp.com/biz/honest-johns-bar-and-grill-detroit?adjust_creative=N0iqFuGe5hug4KyNCfQcCw&utm_campaign=yelp_api_v3&utm_medium=api_v3_business_search&utm_source=N0iqFuGe5hug4KyNCfQcCw",
    "review_count": 574,
    "categories": [
      {
        "alias": "pubs",
        "title": "Pubs"
      },
      {
        "alias": "burgers",
        "title": "Burgers"
      },
      {
        "alias": "breakfast_brunch",
        "title": "Breakfast & Brunch"
      }
    ],
    "rating": 4.0,
    "coordinates": {
      "latitude": 42.3479652404785,
      "longitude": -83.0639419555664
    },
    "transactions": [
      "pickup",
      "delivery"
    ],
    "price": "$$",
    "location": {
      "address1": "488 Selden St",
      "address2": "",
      "address3": "",
      "city": "Detroit",
      "zip_code": "48201",
      "country": "US",
      "state": "MI",
      "display_address": [
        "488 Selden St",
        "Detroit, MI 48201"
      ]
    },
    "phone": "+13138325646",
    "display_phone": "(313) 832-5646",
    "distance": 2756.407792360828
  },
  {
    "id": "4oeL2UZaD9IzIdarbIqfeA",
    "alias": "the-congregation-detroit-detroit",
    "name": "The Congregation Detroit",
    "image_url": "https://s3-media2.fl.yelpcdn.com/bphoto/3Xs9FatVw62WDhOHLXVB4g/o.jpg",
    "is_closed": false,
    "url": "https://www.yelp.com/biz/the-congregation-detroit-detroit?adjust_creative=N0iqFuGe5hug4KyNCfQcCw&utm_campaign=yelp_api_v3&utm_medium=api_v3_business_search&utm_source=N0iqFuGe5hug4KyNCfQcCw",
    "review_count": 104,
    "categories": [
      {
        "alias": "coffee",
        "title": "Coffee & Tea"
      },
      {
        "alias": "cafes",
        "title": "Cafes"
      },
      {
        "alias": "cocktailbars",
        "title": "Cocktail Bars"
      }
    ],
    "rating": 4.5,
    "coordinates": {
      "latitude": 42.377392,
      "longitude": -83.100516
    },
    "transactions": [
      "pickup",
      "delivery"
    ],
    "price": "$$",
    "location": {
      "address1": "9321 Rosa Parks Blvd",
      "address2": null,
      "address3": null,
      "city": "Detroit",
      "zip_code": "48206",
      "country": "US",
      "state": "MI",
      "display_address": [
        "9321 Rosa Parks Blvd",
        "Detroit, MI 48206"
      ]
    },
    "phone": "+13133075518",
    "display_phone": "(313) 307-5518",
    "distance": 1847.8139356208037
  },
  {
    "id": "I-CjgKtXqZ6ccuDFg-czzg",
    "alias": "leila-detroit",
    "name": "Leila",
    "image_url": "https://s3-media1.fl.yelpcdn.com/bphoto/ndySZVnFYsALvvGYVpEZPg/o.jpg",
    "is_closed": false,
    "url": "https://www.yelp.com/biz/leila-detroit?adjust_creative=N0iqFuGe5hug4KyNCfQcCw&utm_campaign=yelp_api_v3&utm_medium=api_v3_business_search&utm_source=N0iqFuGe5hug4KyNCfQcCw",
    "review_count": 196,
    "categories": [
      {
        "alias": "lebanese",
        "title": "Lebanese"
      }
    ],
    "rating": 4.0,
    "coordinates": {
      "latitude": 42.333249,
      "longitude": -83.049995
    },
    "transactions": [
      "delivery"
    ],
    "location": {
      "address1": "1245 Griswold St",
      "address2": "",
      "address3": null,
      "city": "Detroit",
      "zip_code": "48226",
      "country": "US",
      "state": "MI",
      "display_address": [
        "1245 Griswold St",
        "Detroit, MI 48226"
      ]
    },
    "phone": "+13138168100",
    "display_phone": "(313) 816-8100",
    "distance": 4681.884789674646
  },
  {
    "id": "A7qhrIwaUgdwcLD44JY5XA",
    "alias": "san-morello-detroit",
    "name": "San Morello",
    "image_url": "https://s3-media2.fl.yelpcdn.com/bphoto/iz3yAQydUc5JCzE3WjVtrg/o.jpg",
    "is_closed": false,
    "url": "https://www.yelp.com/biz/san-morello-detroit?adjust_creative=N0iqFuGe5hug4KyNCfQcCw&utm_campaign=yelp_api_v3&utm_medium=api_v3_business_search&utm_source=N0iqFuGe5hug4KyNCfQcCw",
    "review_count": 534,
    "categories": [
      {
        "alias": "italian",
        "title": "Italian"
      }
    ],
    "rating": 4.0,
    "coordinates": {
      "latitude": 42.33439,
      "longitude": -83.04848
    },
    "transactions": [
      "pickup",
      "delivery"
    ],
    "price": "$$$",
    "location": {
      "address1": "1400 Woodward Ave",
      "address2": null,
      "address3": "",
      "city": "Detroit",
      "zip_code": "48226",
      "country": "US",
      "state": "MI",
      "display_address": [
        "1400 Woodward Ave",
        "Detroit, MI 48226"
      ]
    },
    "phone": "+13132094700",
    "display_phone": "(313) 209-4700",
    "distance": 4686.8334913577
  },
  {
    "id": "XMieCaQ9NofNrzSl9FsOqg",
    "alias": "pao-detroit-detroit",
    "name": "PAO Detroit",
    "image_url": "https://s3-media1.fl.yelpcdn.com/bphoto/stuAFrS-O1y1lKoEQb9nKQ/o.jpg",
    "is_closed": false,
    "url": "https://www.yelp.com/biz/pao-detroit-detroit?adjust_creative=N0iqFuGe5hug4KyNCfQcCw&utm_campaign=yelp_api_v3&utm_medium=api_v3_business_search&utm_source=N0iqFuGe5hug4KyNCfQcCw",
    "review_count": 281,
    "categories": [
      {
        "alias": "asianfusion",
        "title": "Asian Fusion"
      },
      {
        "alias": "panasian",
        "title": "Pan Asian"
      }
    ],
    "rating": 3.5,
    "coordinates": {
      "latitude": 42.33632,
      "longitude": -83.053074
    },
    "transactions": [
      "pickup",
      "delivery"
    ],
    "price": "$$",
    "location": {
      "address1": "114 West Adams Ave",
      "address2": "Ste 200",
      "address3": "",
      "city": "Detroit",
      "zip_code": "48226",
      "country": "US",
      "state": "MI",
      "display_address": [
        "114 West Adams Ave",
        "Ste 200",
        "Detroit, MI 48226"
      ]
    },
    "phone": "+13138160000",
    "display_phone": "(313) 816-0000",
    "distance": 4263.317046756562
  },
  {
    "id": "jDHPcMstUfhnbp-4dVm7YQ",
    "alias": "savannahblue-detroit-2",
    "name": "SavannahBlue",
    "image_url": "https://s3-media1.fl.yelpcdn.com/bphoto/mNg6TI6O8kyrWK-s2_Un9A/o.jpg",
    "is_closed": false,
    "url": "https://www.yelp.com/biz/savannahblue-detroit-2?adjust_creative=N0iqFuGe5hug4KyNCfQcCw&utm_campaign=yelp_api_v3&utm_medium=api_v3_business_search&utm_source=N0iqFuGe5hug4KyNCfQcCw",
    "review_count": 561,
    "categories": [
      {
        "alias": "newamerican",
        "title": "American (New)"
      },
      {
        "alias": "soulfood",
        "title": "Soul Food"
      },
      {
        "alias": "cocktailbars",
        "title": "Cocktail Bars"
      }
    ],
    "rating": 4.0,
    "coordinates": {
      "latitude": 42.3341913,
      "longitude": -83.05233
    },
    "transactions": [
      "pickup",
      "delivery"
    ],
    "price": "$$",
    "location": {
      "address1": "1431 Times Square",
      "address2": "",
      "address3": "",
      "city": "Detroit",
      "zip_code": "48226",
      "country": "US",
      "state": "MI",
      "display_address": [
        "1431 Times Square",
        "Detroit, MI 48226"
      ]
    },
    "phone": "+13139260783",
    "display_phone": "(313) 926-0783",
    "distance": 4471.467461249371
  },
  {
    "id": "WiKKNXaHC4Zino2A1m3ftQ",
    "alias": "royale-with-cheese-detroit",
    "name": "Royale with Cheese",
    "image_url": "https://s3-media1.fl.yelpcdn.com/bphoto/nNPfqOgpImR6jfufBwnTvQ/o.jpg",
    "is_closed": false,
    "url": "https://www.yelp.com/biz/royale-with-cheese-detroit?adjust_creative=N0iqFuGe5hug4KyNCfQcCw&utm_campaign=yelp_api_v3&utm_medium=api_v3_business_search&utm_source=N0iqFuGe5hug4KyNCfQcCw",
    "review_count": 623,
    "categories": [
      {
        "alias": "burgers",
        "title": "Burgers"
      }
    ],
    "rating": 4.0,
    "coordinates": {
      "latitude": 42.350337903122,
      "longitude": -83.0634118616581
    },
    "transactions": [
      "pickup",
      "delivery"
    ],
    "price": "$$",
    "location": {
      "address1": "4163 Cass Ave",
      "address2": "",
      "address3": null,
      "city": "Detroit",
      "zip_code": "48201",
      "country": "US",
      "state": "MI",
      "display_address": [
        "4163 Cass Ave",
        "Detroit, MI 48201"
      ]
    },
    "phone": "+13133153014",
    "display_phone": "(313) 315-3014",
    "distance": 2637.053969422288
  },
  {
    "id": "d-5lyKTcTy10JSrBnR3q0A",
    "alias": "freya-detroit",
    "name": "Freya",
    "image_url": "https://s3-media3.fl.yelpcdn.com/bphoto/f7paso4_IHY5oNFO-HTJ6A/o.jpg",
    "is_closed": false,
    "url": "https://www.yelp.com/biz/freya-detroit?adjust_creative=N0iqFuGe5hug4KyNCfQcCw&utm_campaign=yelp_api_v3&utm_medium=api_v3_business_search&utm_source=N0iqFuGe5hug4KyNCfQcCw",
    "review_count": 60,
    "categories": [
      {
        "alias": "newamerican",
        "title": "American (New)"
      },
      {
        "alias": "tradamerican",
        "title": "American (Traditional)"
      }
    ],
    "rating": 4.5,
    "coordinates": {
      "latitude": 42.372168868609904,
      "longitude": -83.0669829
    },
    "transactions": [],
    "location": {
      "address1": "2929 E Grand Blvd",
      "address2": null,
      "address3": "",
      "city": "Detroit",
      "zip_code": "48202",
      "country": "US",
      "state": "MI",
      "display_address": [
        "2929 E Grand Blvd",
        "Detroit, MI 48202"
      ]
    },
    "phone": "+13133515544",
    "display_phone": "(313) 351-5544",
    "distance": 2242.120821417601
  },
  {
    "id": "kgXy9XwRanK8mfOuxQP1gA",
    "alias": "besa-detroit",
    "name": "Besa",
    "image_url": "https://s3-media2.fl.yelpcdn.com/bphoto/c836VTJ1b7gIrfjO5MmiLg/o.jpg",
    "is_closed": false,
    "url": "https://www.yelp.com/biz/besa-detroit?adjust_creative=N0iqFuGe5hug4KyNCfQcCw&utm_campaign=yelp_api_v3&utm_medium=api_v3_business_search&utm_source=N0iqFuGe5hug4KyNCfQcCw",
    "review_count": 201,
    "categories": [
      {
        "alias": "newamerican",
        "title": "American (New)"
      },
      {
        "alias": "seafood",
        "title": "Seafood"
      },
      {
        "alias": "salad",
        "title": "Salad"
      }
    ],
    "rating": 4.0,
    "coordinates": {
      "latitude": 42.33052,
      "longitude": -83.04533
    },
    "transactions": [
      "pickup",
      "delivery"
    ],
    "price": "$$$",
    "location": {
      "address1": "600 Woodward Ave",
      "address2": "",
      "address3": null,
      "city": "Detroit",
      "zip_code": "48226",
      "country": "US",
      "state": "MI",
      "display_address": [
        "600 Woodward Ave",
        "Detroit, MI 48226"
      ]
    },
    "phone": "+13133153000",
    "display_phone": "(313) 315-3000",
    "distance": 5168.703986524795
  },
  {
    "id": "gwRDH8gr9Iu_mvMkaYAoVg",
    "alias": "folk-detroit-2",
    "name": "Folk",
    "image_url": "https://s3-media4.fl.yelpcdn.com/bphoto/VcDd_EN1uqHoABx2ahWXew/o.jpg",
    "is_closed": false,
    "url": "https://www.yelp.com/biz/folk-detroit-2?adjust_creative=N0iqFuGe5hug4KyNCfQcCw&utm_campaign=yelp_api_v3&utm_medium=api_v3_business_search&utm_source=N0iqFuGe5hug4KyNCfQcCw",
    "review_count": 128,
    "categories": [
      {
        "alias": "breakfast_brunch",
        "title": "Breakfast & Brunch"
      },
      {
        "alias": "cafes",
        "title": "Cafes"
      },
      {
        "alias": "wine_bars",
        "title": "Wine Bars"
      }
    ],
    "rating": 4.0,
    "coordinates": {
      "latitude": 42.32955639204327,
      "longitude": -83.06589326540679
    },
    "transactions": [
      "pickup",
      "delivery"
    ],
    "price": "$$",
    "location": {
      "address1": "1701 Trumbull Ave",
      "address2": "",
      "address3": null,
      "city": "Detroit",
      "zip_code": "48216",
      "country": "US",
      "state": "MI",
      "display_address": [
        "1701 Trumbull Ave",
        "Detroit, MI 48216"
      ]
    },
    "phone": "+13137422672",
    "display_phone": "(313) 742-2672",
    "distance": 4204.120613110192
  },
  {
    "id": "7bhpcorU3CAd33KJefB0EQ",
    "alias": "mink-detroit",
    "name": "Mink",
    "image_url": "https://s3-media2.fl.yelpcdn.com/bphoto/FS0Uc_o2zaxCgc9SnSAgpQ/o.jpg",
    "is_closed": false,
    "url": "https://www.yelp.com/biz/mink-detroit?adjust_creative=N0iqFuGe5hug4KyNCfQcCw&utm_campaign=yelp_api_v3&utm_medium=api_v3_business_search&utm_source=N0iqFuGe5hug4KyNCfQcCw",
    "review_count": 57,
    "categories": [
      {
        "alias": "seafood",
        "title": "Seafood"
      },
      {
        "alias": "wine_bars",
        "title": "Wine Bars"
      }
    ],
    "rating": 4.5,
    "coordinates": {
      "latitude": 42.329556,
      "longitude": -83.065869
    },
    "transactions": [
      "delivery"
    ],
    "location": {
      "address1": "1701 Trumbull",
      "address2": "Ste D",
      "address3": null,
      "city": "Detroit",
      "zip_code": "48216",
      "country": "US",
      "state": "MI",
      "display_address": [
        "1701 Trumbull",
        "Ste D",
        "Detroit, MI 48216"
      ]
    },
    "phone": "+13133796465",
    "display_phone": "(313) 379-6465",
    "distance": 4206.266817976277
  },
  {
    "id": "4U4GNiJgT4laE9VHmodvJA",
    "alias": "marrow-detroit",
    "name": "Marrow",
    "image_url": "https://s3-media3.fl.yelpcdn.com/bphoto/eK9dY3rt3jcsz24g-yN94Q/o.jpg",
    "is_closed": false,
    "url": "https://www.yelp.com/biz/marrow-detroit?adjust_creative=N0iqFuGe5hug4KyNCfQcCw&utm_campaign=yelp_api_v3&utm_medium=api_v3_business_search&utm_source=N0iqFuGe5hug4KyNCfQcCw",
    "review_count": 296,
    "categories": [
      {
        "alias": "newamerican",
        "title": "American (New)"
      },
      {
        "alias": "butcher",
        "title": "Butcher"
      }
    ],
    "rating": 4.5,
    "coordinates": {
      "latitude": 42.35852,
      "longitude": -82.99882
    },
    "transactions": [],
    "price": "$$$$",
    "location": {
      "address1": "8044 Kercheval Ave",
      "address2": "1B",
      "address3": "",
      "city": "Detroit",
      "zip_code": "48214",
      "country": "US",
      "state": "MI",
      "display_address": [
        "8044 Kercheval Ave",
        "1B",
        "Detroit, MI 48214"
      ]
    },
    "phone": "+13136520200",
    "display_phone": "(313) 652-0200",
    "distance": 7575.073099610667
  },
  {
    "id": "n_QyiAUeW8cVNfVvA3GpdQ",
    "alias": "vertical-detroit-detroit",
    "name": "Vertical Detroit",
    "image_url": "https://s3-media1.fl.yelpcdn.com/bphoto/2r9WCpqAb6M30CTjOl-UvQ/o.jpg",
    "is_closed": false,
    "url": "https://www.yelp.com/biz/vertical-detroit-detroit?adjust_creative=N0iqFuGe5hug4KyNCfQcCw&utm_campaign=yelp_api_v3&utm_medium=api_v3_business_search&utm_source=N0iqFuGe5hug4KyNCfQcCw",
    "review_count": 415,
    "categories": [
      {
        "alias": "wine_bars",
        "title": "Wine Bars"
      },
      {
        "alias": "newamerican",
        "title": "American (New)"
      },
      {
        "alias": "steak",
        "title": "Steakhouses"
      }
    ],
    "rating": 4.0,
    "coordinates": {
      "latitude": 42.336328308655276,
      "longitude": -83.04716327054949
    },
    "transactions": [
      "delivery"
    ],
    "price": "$$$",
    "location": {
      "address1": "1538 Centre St",
      "address2": "",
      "address3": "",
      "city": "Detroit",
      "zip_code": "48226",
      "country": "US",
      "state": "MI",
      "display_address": [
        "1538 Centre St",
        "Detroit, MI 48226"
      ]
    },
    "phone": "+13137329463",
    "display_phone": "(313) 732-9463",
    "distance": 4629.067022075474
  }
]